main.py
pyroute53myip/__init__.py
pyroute53myip/pyroute53myip.py
pyroute53myip-0.0.2.dist-info/LICENSE
pyroute53myip-0.0.2.dist-info/METADATA
pyroute53myip-0.0.2.dist-info/WHEEL
pyroute53myip-0.0.2.dist-info/entry_points.txt
pyroute53myip-0.0.2.dist-info/top_level.txt
pyroute53myip-0.0.2.dist-info/RECORD
