Metadata-Version: 2.1
Name: pyroute53myip
Version: 0.0.2
Summary: This python tool pyroute53myip is useful to allow automate updating of a public DNS record hosted at Internet based in the public internet address from home. It is a quite typical scenario running at a domestic raspberry-pi tiny instance
Author-email: redcorjo <jordipromotions@gmail.com>
Project-URL: Homepage, https://github.com/redcorjo/pyroute53myip
Project-URL: Bug Tracker, https://github.com/redcorjo/pyroute53myip/issues
Classifier: Programming Language :: Python :: 3
Classifier: License :: OSI Approved :: MIT License
Classifier: Operating System :: OS Independent
Requires-Python: >=3.7
License-File: LICENSE
Requires-Dist: boto3
Requires-Dist: dnspython
Requires-Dist: paho-mqtt
Requires-Dist: pyeasyencrypt
Requires-Dist: APScheduler
